NER/__init__.py
NER/ner_common/__init__.py
NER/ner_common/components.py
NER/ner_common/utils.py
NER/tplinker_ner/LocationClueExtracting.py
NER/tplinker_ner/__init__.py
NER/tplinker_ner/tplinker_ner.py
yucheng_ner/__init__.py
yucheng_ner/ner_common/__init__.py
yucheng_ner/ner_common/components.py
yucheng_ner/ner_common/utils.py
yucheng_ner/tplinker_ner/LocationClueExtracting.py
yucheng_ner/tplinker_ner/__init__.py
yucheng_ner/tplinker_ner/tplinker_ner.py
yucheng_ner-0.6.dist-info/LICENSE.txt
yucheng_ner-0.6.dist-info/METADATA
yucheng_ner-0.6.dist-info/WHEEL
yucheng_ner-0.6.dist-info/top_level.txt
yucheng_ner-0.6.dist-info/RECORD
