Metadata-Version: 2.1
Name: yucheng-ner
Version: 0.6
Summary: Named Entities Recognition by Token Pair Linking
Home-page: https://github.com/131250208/yucheng_ner
Author: Andy Wong
Author-email: wangyucheng@iie.ac.cn
License: MIT
Platform: UNKNOWN
Classifier: License :: OSI Approved :: MIT License
Classifier: Programming Language :: Python
Classifier: Programming Language :: Python :: 3
Classifier: Programming Language :: Python :: 3.6
Classifier: Programming Language :: Python :: Implementation :: CPython
Classifier: Programming Language :: Python :: Implementation :: PyPy
Requires-Python: >=3.6.0
Requires-Dist: flair
Requires-Dist: torch
Requires-Dist: pyyaml
Requires-Dist: word2vec
Requires-Dist: tqdm
Requires-Dist: glove-python-binary (==0.2.0)
Requires-Dist: transformers (==3.0.2)
Requires-Dist: wandb
